bioticDETR/__init__.py
bioticDETR/__main__.py
bioticDETR-1.0.0.dev0.dist-info/METADATA
bioticDETR-1.0.0.dev0.dist-info/WHEEL
bioticDETR-1.0.0.dev0.dist-info/top_level.txt
bioticDETR-1.0.0.dev0.dist-info/RECORD
